Incubate/Common.py
Incubate/Http.py
Incubate/Journal.py
Incubate/Resource.py
Incubate/Scheduler.py
Incubate/Websocket.py
Incubate/__init__.py
incubate-1.0.1.dist-info/licenses/LICENSE
incubate-1.0.1.dist-info/METADATA
incubate-1.0.1.dist-info/WHEEL
incubate-1.0.1.dist-info/top_level.txt
incubate-1.0.1.dist-info/RECORD
