Metadata-Version: 2.4
Name: Incubate
Version: 1.0.1
Summary: A Multi Port, Multi Process, Multi Coroutine, High Concurrency Project.
Author-email: Yip bell <yif8081@gmail.com>
License: MIT
Requires-Python: >=3.10
License-File: LICENSE
Requires-Dist: orjson>=3.11.0
Requires-Dist: psutil>=7.0.0
Requires-Dist: setproctitle>=1.3.0
Requires-Dist: uvloop>=0.21.0; sys_platform != "win32"
Dynamic: license-file
